rs_common_interfaces_py/__init__.py
rs_common_interfaces_py/conversion.py
rs_common_interfaces_py/py.typed
rs_common_interfaces_py/request.py
rs_common_interfaces_py/video.py
rs_common_interfaces_py-0.1.7.dist-info/METADATA
rs_common_interfaces_py-0.1.7.dist-info/WHEEL
rs_common_interfaces_py-0.1.7.dist-info/licenses/LICENSE
rs_common_interfaces_py-0.1.7.dist-info/RECORD
